denofo/__init__.py
denofo/choices.py
denofo/models.py
denofo/comparator/__init__.py
denofo/comparator/comparator_cli.py
denofo/comparator/comparator_gui.py
denofo/comparator/compare.py
denofo/converter/__init__.py
denofo/converter/convert.py
denofo/converter/converter_cli.py
denofo/converter/converter_gui.py
denofo/questionnaire/__init__.py
denofo/questionnaire/questionnaire_cli.py
denofo/questionnaire/questionnaire_gui.py
denofo/questionnaire/questions.py
denofo/static/denofo-logo.jpg
denofo/utils/__init__.py
denofo/utils/constants.py
denofo/utils/helpers.py
denofo/utils/ncbiTaxDBcheck.py
denofo-0.9.3.dist-info/METADATA
denofo-0.9.3.dist-info/WHEEL
denofo-0.9.3.dist-info/entry_points.txt
denofo-0.9.3.dist-info/licenses/LICENSE
denofo-0.9.3.dist-info/RECORD
