Metadata-Version: 2.4
Name: denofo
Version: 0.9.3
Summary: A toolkit to easily access, convert and compare the de novo gene annotation format (denofo).
Author-email: Elias Dohmen <e.dohmen@uni-muenster.de>
License-File: LICENSE
Requires-Python: <3.13,>=3.11
Requires-Dist: argparse>=1.4.0
Requires-Dist: biopython>=1.85
Requires-Dist: ete3>=3.1.3
Requires-Dist: pathlib>=1.0.1
Requires-Dist: pydantic>=2.10.5
Requires-Dist: pyqt6>=6.8.1
Requires-Dist: six>=1.17.0
Requires-Dist: windows-curses>=2.4.1; sys_platform == 'windows'
